pidsim
